jupyterlab_block_copy/__init__.py
jupyterlab_block_copy/_version.py
jupyterlab_block_copy-0.1.2.data/data/share/jupyter/labextensions/jupyterlab_block_copy/build_log.json
jupyterlab_block_copy-0.1.2.data/data/share/jupyter/labextensions/jupyterlab_block_copy/package.json
jupyterlab_block_copy-0.1.2.data/data/share/jupyter/labextensions/jupyterlab_block_copy/static/lib_index_js.afab220a9816ed81efa1.js
jupyterlab_block_copy-0.1.2.data/data/share/jupyter/labextensions/jupyterlab_block_copy/static/lib_index_js.afab220a9816ed81efa1.js.map
jupyterlab_block_copy-0.1.2.data/data/share/jupyter/labextensions/jupyterlab_block_copy/static/remoteEntry.8a18b65179b1197b7e9d.js
jupyterlab_block_copy-0.1.2.data/data/share/jupyter/labextensions/jupyterlab_block_copy/static/remoteEntry.8a18b65179b1197b7e9d.js.map
jupyterlab_block_copy-0.1.2.data/data/share/jupyter/labextensions/jupyterlab_block_copy/static/style.js
jupyterlab_block_copy-0.1.2.data/data/share/jupyter/labextensions/jupyterlab_block_copy/static/style_index_js.0fb6d269f4b30d432d8f.js
jupyterlab_block_copy-0.1.2.data/data/share/jupyter/labextensions/jupyterlab_block_copy/static/style_index_js.0fb6d269f4b30d432d8f.js.map
jupyterlab_block_copy-0.1.2.data/data/share/jupyter/labextensions/jupyterlab_block_copy/install.json
jupyterlab_block_copy-0.1.2.dist-info/METADATA
jupyterlab_block_copy-0.1.2.dist-info/WHEEL
jupyterlab_block_copy-0.1.2.dist-info/licenses/LICENSE
jupyterlab_block_copy-0.1.2.dist-info/RECORD
