Metadata-Version: 2.4
Name: jupyterlab_block_copy
Version: 0.1.2
Summary: A JupyterLab extension. block copy/cut events in jupyterLab
Project-URL: Homepage, https://github.com/MrNeo8x/jupyterlab_block_copy
Project-URL: Bug Tracker, https://github.com/MrNeo8x/jupyterlab_block_copy/issues
Project-URL: Repository, https://github.com/MrNeo8x/jupyterlab_block_copy.git
Author-email: Quan Vu Nam <vu.nam.87@gmail.com>
License: BSD 3-Clause License
License-File: LICENSE
Keywords: jupyter,jupyterlab,jupyterlab-extension
Classifier: Framework :: Jupyter
Classifier: Framework :: Jupyter :: JupyterLab
Classifier: Framework :: Jupyter :: JupyterLab :: 4
Classifier: Framework :: Jupyter :: JupyterLab :: Extensions
Classifier: Framework :: Jupyter :: JupyterLab :: Extensions :: Prebuilt
Classifier: License :: OSI Approved :: BSD License
Classifier: Programming Language :: Python
Classifier: Programming Language :: Python :: 3
Classifier: Programming Language :: Python :: 3.9
Classifier: Programming Language :: Python :: 3.10
Classifier: Programming Language :: Python :: 3.11
Classifier: Programming Language :: Python :: 3.12
Classifier: Programming Language :: Python :: 3.13
Requires-Python: >=3.9
